{
  "strategy": "chinese",
  "matchStrategy": "prefix",
  "maxNumberOfSuggestions": 5,
  "maxNumberOfWordsAsPhrase": 3,
  "minNumberOfCharactersTriggered": 0,
  "minNumberOfWordsTriggeredPhrase": 1,
  "complementAutomatically": true,
  "delayMilliSeconds": 0,
  "disableSuggestionsDuringImeOn": false,
  "insertAfterCompletion": true,
  "firstCharactersDisableSuggestions": ":/^",
  "showMatchStrategy": true,
  "showComplementAutomatically": true,
  "showIndexingStatus": true,
  "descriptionOnSuggestion": "Short",
  "selectSuggestionKeys": "Enter",
  "additionalCycleThroughSuggestionsKeys": "None",
  "disableUpDownKeysForCycleThroughSuggestionsKeys": false,
  "openSourceFileKey": "None",
  "propagateEsc": false,
  "enableCurrentFileComplement": true,
  "currentFileMinNumberOfCharacters": 0,
  "onlyComplementEnglishOnCurrentFileComplement": false,
  "enableCurrentVaultComplement": false,
  "currentVaultMinNumberOfCharacters": 0,
  "includeCurrentVaultPathPrefixPatterns": "",
  "excludeCurrentVaultPathPrefixPatterns": "",
  "includeCurrentVaultOnlyFilesUnderCurrentDirectory": false,
  "enableCustomDictionaryComplement": false,
  "customDictionaryPaths": "https://raw.githubusercontent.com/first20hours/google-10000-english/master/google-10000-english-no-swears.txt",
  "columnDelimiter": "Tab",
  "customDictionaryWordRegexPattern": "",
  "delimiterToHideSuggestion": "",
  "delimiterToDivideSuggestionsForDisplayFromInsertion": "",
  "caretLocationSymbolAfterComplement": "",
  "displayedTextSuffix": " => ...",
  "enableInternalLinkComplement": true,
  "suggestInternalLinkWithAlias": false,
  "excludeInternalLinkPathPrefixPatterns": "",
  "enableFrontMatterComplement": true,
  "frontMatterComplementMatchStrategy": "inherit",
  "insertCommaAfterFrontMatterCompletion": false,
  "intelligentSuggestionPrioritization": {
    "maxDaysToKeepHistory": 30,
    "maxNumberOfHistoryToKeep": 0
  },
  "showLogAboutPerformanceInConsole": false,
  "selectionHistoryTree": {
    "配伍": {
      "配伍": {
        "currentFile": {
          "count": 1,
          "lastUpdated": 1681089013321
        }
      }
    },
    "相反": {
      "相反": {
        "internalLink": {
          "count": 1,
          "lastUpdated": 1681089130895
        }
      }
    },
    "砂仁": {
      "砂仁": {
        "currentFile": {
          "count": 1,
          "lastUpdated": 1681089592070
        }
      }
    },
    "不同": {
      "不同": {
        "currentFile": {
          "count": 1,
          "lastUpdated": 1681089648297
        }
      }
    },
    "毒性": {
      "毒性": {
        "currentFile": {
          "count": 3,
          "lastUpdated": 1681089689688
        }
      }
    },
    "黄芩": {
      "黄芩": {
        "internalLink": {
          "count": 1,
          "lastUpdated": 1681089803792
        }
      }
    },
    "津液辩证": {
      "津液辩证": {
        "internalLink": {
          "count": 1,
          "lastUpdated": 1681107597508
        }
      }
    },
    "明显": {
      "明显": {
        "currentFile": {
          "count": 1,
          "lastUpdated": 1681107655602
        }
      }
    },
    "三魂": {
      "三魂": {
        "currentFile": {
          "count": 1,
          "lastUpdated": 1681113014681
        }
      }
    },
    "能力": {
      "能力": {
        "currentFile": {
          "count": 1,
          "lastUpdated": 1681113415339
        }
      }
    },
    "停顿": {
      "停顿": {
        "currentFile": {
          "count": 1,
          "lastUpdated": 1681113508443
        }
      }
    },
    "人性的弱点": {
      "人性的弱点": {
        "internalLink": {
          "count": 1,
          "lastUpdated": 1681175188585
        }
      }
    },
    "地图不是领土": {
      "地图不是领土": {
        "internalLink": {
          "count": 1,
          "lastUpdated": 1681175694530
        }
      }
    },
    "中药": {
      "中药": {
        "internalLink": {
          "count": 1,
          "lastUpdated": 1681176859219
        }
      }
    },
    "过程": {
      "过程": {
        "currentFile": {
          "count": 1,
          "lastUpdated": 1681176940026
        }
      }
    },
    "结果": {
      "结果": {
        "currentFile": {
          "count": 1,
          "lastUpdated": 1681176943578
        }
      }
    },
    "二阶思维": {
      "二阶思维": {
        "internalLink": {
          "count": 1,
          "lastUpdated": 1681176965947
        }
      }
    },
    "好的作品": {
      "好的作品": {
        "internalLink": {
          "count": 1,
          "lastUpdated": 1681177060676
        }
      }
    },
    "业余爱好者": {
      "业余爱好者": {
        "currentFile": {
          "count": 2,
          "lastUpdated": 1681177220779
        }
      }
    },
    "责任": {
      "责任": {
        "currentFile": {
          "count": 1,
          "lastUpdated": 1681177114996
        }
      }
    },
    "出现": {
      "出现": {
        "currentFile": {
          "count": 1,
          "lastUpdated": 1681177127139
        }
      }
    },
    "目标": {
      "目标": {
        "currentFile": {
          "count": 1,
          "lastUpdated": 1681178264368
        }
      }
    },
    "水饮": {
      "水饮": {
        "internalLink": {
          "count": 1,
          "lastUpdated": 1681180823400
        }
      }
    },
    "湿热蕴脾证": {
      "湿热蕴脾证": {
        "internalLink": {
          "count": 1,
          "lastUpdated": 1681180894495
        }
      }
    },
    "字体": {
      "字体": {
        "currentFile": {
          "count": 1,
          "lastUpdated": 1681347186861
        }
      }
    },
    "阅读时间": {
      "阅读时间": {
        "currentFile": {
          "count": 1,
          "lastUpdated": 1681347271246
        }
      }
    },
    "调换": {
      "调换": {
        "currentFile": {
          "count": 1,
          "lastUpdated": 1681347605774
        }
      }
    },
    "命名": {
      "命名": {
        "currentFile": {
          "count": 1,
          "lastUpdated": 1681347952708
        }
      }
    },
    "标注": {
      "标注": {
        "currentFile": {
          "count": 2,
          "lastUpdated": 1681348479296
        }
      }
    },
    "参考左侧列": {
      "参考左侧列": {
        "internalLink": {
          "count": 1,
          "lastUpdated": 1681348833062
        }
      }
    }
  }
}